WeakLIA/__init__.py
WeakLIA/cnn_model.py
WeakLIA/data_augmentation.py
WeakLIA/data_processing.py
WeakLIA/optimization.py
WeakLIA/data/__init__.py
WeakLIA-0.11.dist-info/LICENSE.txt
WeakLIA-0.11.dist-info/METADATA
WeakLIA-0.11.dist-info/WHEEL
WeakLIA-0.11.dist-info/top_level.txt
WeakLIA-0.11.dist-info/RECORD
